<?xml version="1.0" encoding="UTF-8"?>
<!DOCTYPE language SYSTEM "DTD/language.dtd">
<!-- $Id$ -->
<language languagecode="en">
	<category name="wbb.portal">
		<item name="wbb.portal.box.wbb3addonsBox02.title"><![CDATA[wBB3-Add-Ons Box 2]]></item>
	</category>
	<category name="wcf.acp.option">
		<item name="wcf.acp.option.category.portal.box.wbb3addonsBox02"><![CDATA[wBB3-Add-Ons Box 2]]></item>
		<item name="wcf.acp.option.category.portal.box.wbb3addonsBox02.description"><![CDATA[]]></item>
		<item name="wcf.acp.option.wbb3addonsBox02_title"><![CDATA[Title]]></item>
		<item name="wcf.acp.option.wbb3addonsBox02_title.description"><![CDATA[]]></item>
		<item name="wcf.acp.option.wbb3addonsBox02_value"><![CDATA[Content]]></item>
		<item name="wcf.acp.option.wbb3addonsBox02_value.description"><![CDATA[]]></item>
		<item name="wcf.acp.option.wbb3addonsBox02_php"><![CDATA[PHP-Code]]></item>
		<item name="wcf.acp.option.wbb3addonsBox02_php.description"><![CDATA[]]></item>
		<item name="wcf.acp.option.wbb3addonsBox02_boxOpened"><![CDATA[Box permanently opened]]></item>
		<item name="wcf.acp.option.wbb3addonsBox02_boxOpened.description"><![CDATA[]]></item>
	</category>
</language>
